tests/__init__.py
tests/test_inference.py
tests/test_server.py
text_generation_api/__init__.py
text_generation_api/cmd.py
text_generation_api/default.py
text_generation_api/endpoint.py
text_generation_api/inference.py
text_generation_api/server.py
text_generation_api/utils.py
text_generation_api-0.0.1.dist-info/LICENSE
text_generation_api-0.0.1.dist-info/METADATA
text_generation_api-0.0.1.dist-info/WHEEL
text_generation_api-0.0.1.dist-info/entry_points.txt
text_generation_api-0.0.1.dist-info/top_level.txt
text_generation_api-0.0.1.dist-info/RECORD
