Metadata-Version: 2.1
Name: text-generation-api
Version: 0.0.1
Home-page: 
Author: Federico A. Galatolo
Author-email: federico.galatolo@unipi.it
Classifier: Programming Language :: Python :: 3.8
Classifier: License :: OSI Approved :: GNU General Public License v3 (GPLv3)
Classifier: Operating System :: OS Independent
Classifier: Development Status :: 4 - Beta
License-File: LICENSE
Requires-Dist: transformers (==4.29.2)
Requires-Dist: PyYAML (==6.0)
Requires-Dist: fastapi (==0.95.2)
Requires-Dist: uvicorn (==0.22.0)
Requires-Dist: httpx (==0.24.1)
